sky/__init__.py
sky/autho_dict_maker.py
sky/cache.py
sky/configs.py
sky/crawlconfig.py
sky/crawler_plugins.py
sky/crawler_services.py
sky/dbpedia.py
sky/examples.py
sky/findTitle.py
sky/get_author.py
sky/get_date.py
sky/handle_dbpedia.py
sky/helper.py
sky/images.py
sky/language.py
sky/links.py
sky/log.py
sky/money.py
sky/month_dict_maker.py
sky/opener.py
sky/remove_boilerplate.py
sky/scraper.py
sky/sky.py
sky/crawler/__init__.py
sky/crawler/crawl.py
sky/crawler/crawling.py
sky/crawler/reporting.py
sky/crawler/test.py
sky/data/__init__.py
sky/data/author_translation_table.json
sky/data/date_translation_table.json
sky/view/__init__.py
sky/view/view.py
sky/view/static/css/app.css
sky/view/static/css/bootplus-responsive.css
sky/view/static/css/bootplus.css
sky/view/static/js/app.js
sky/view/static/js/bootstrap.min.js
sky/view/static/js/jquery-2.1.1.min.js
sky/view/templates/addurl.html
sky/view/templates/head.html
sky/view/templates/index.html
sky/view/templates/menu.html
sky/view/templates/page_template.html
sky/view/templates/result.html
sky-0.0.201.dist-info/METADATA
sky-0.0.201.dist-info/RECORD
sky-0.0.201.dist-info/WHEEL
sky-0.0.201.dist-info/entry_points.txt
sky-0.0.201.dist-info/top_level.txt
