Metadata-Version: 2.1
Name: sky
Version: 0.0.201
Summary: AI powered scraping in Python 3
Home-page: https://github.com/kootenpv/sky
Author: Pascal van Kooten
Author-email: kootenpv@gmail.com
License: BSD
Platform: any
Classifier: Environment :: Console
Classifier: Intended Audience :: Developers
Classifier: Intended Audience :: Customer Service
Classifier: Intended Audience :: System Administrators
Classifier: License :: OSI Approved :: GNU General Public License v3 (GPLv3)
Classifier: Operating System :: Microsoft
Classifier: Operating System :: MacOS :: MacOS X
Classifier: Operating System :: Unix
Classifier: Operating System :: POSIX
Classifier: Programming Language :: Python
Classifier: Programming Language :: Python :: 3.5
Classifier: Programming Language :: Python :: 3.6
Classifier: Programming Language :: Python :: 3.7
Classifier: Topic :: Software Development
Classifier: Topic :: Software Development :: Build Tools
Classifier: Topic :: Software Development :: Debuggers
Classifier: Topic :: Software Development :: Libraries
Classifier: Topic :: Software Development :: Libraries :: Python Modules
Classifier: Topic :: System :: Software Distribution
Classifier: Topic :: System :: Systems Administration
Classifier: Topic :: Utilities
Requires-Dist: lxml
Requires-Dist: tldextract
Requires-Dist: requests
Requires-Dist: justext
Requires-Dist: langdetect
Requires-Dist: python-dateutil
Requires-Dist: beautifulsoup4
Requires-Dist: aiohttp
Requires-Dist: tornado (==4.5.3)
